anomalous/__init__.py
anomalous/constants.py
anomalous/mannually_label_anomalies.py
anomalous/random_forest.py
anomalous/settings.py
anomalous/urls.py
anomalous/utils.py
anomalous/viz.py
anomalous/viz_iris.py
anomalous/wsgi.py
anomalous/data/time-series.html
anomalous/scripts/__init__.py
anomalous/scripts/chasedown.py
anomalous/scripts/install.sh
anomalous-0.0.16.dist-info/DESCRIPTION.rst
anomalous-0.0.16.dist-info/METADATA
anomalous-0.0.16.dist-info/RECORD
anomalous-0.0.16.dist-info/WHEEL
anomalous-0.0.16.dist-info/dependency_links.txt
anomalous-0.0.16.dist-info/entry_points.txt
anomalous-0.0.16.dist-info/metadata.json
anomalous-0.0.16.dist-info/top_level.txt
