Metadata-Version: 2.0
Name: anomalous
Version: 0.0.16
Summary: Server anomaly detection.
Home-page: http://authoritylabs.com
Author: Hobson Lane
Author-email: github@totalgood.com
License: none
Platform: UNKNOWN
Classifier: Development Status :: 4 - Beta
Classifier: Programming Language :: Python
Classifier: Programming Language :: Python :: 3
Classifier: Topic :: Scientific/Engineering :: Mathematics
Classifier: Topic :: Scientific/Engineering :: Visualization
Classifier: Topic :: Scientific/Engineering :: Information Analysis
Classifier: Topic :: Internet :: Log Analysis
Classifier: Topic :: System :: Monitoring
Classifier: Topic :: System :: Networking :: Monitoring
Requires-Dist: nlpia
Requires-Dist: timestring (>=1.6.2)
Requires-Dist: datadog (==0.16.0)
Requires-Dist: dogapi (==1.11.1)
Requires-Dist: TA-Lib (==0.4.10)
Requires-Dist: igraph (==0.1.11)
